{"cameraMode":{"drawMode":0,"name":"Shaded","section":"Shading Mode"},"sceneLighting":true,"audioPlay":false,"sceneViewState":{"showFog":true,"showMaterialUpdate":false,"showSkybox":true,"showFlares":true,"showImageEffects":true,"showParticleSystems":true},"in2DMode":false,"pivot":{"x":-0.1508570909500122,"y":0.06739962100982666,"z":27.318748474121095},"rotation":{"x":-0.3035251498222351,"y":-0.5365453362464905,"z":0.21487955749034882,"w":-0.7576335668563843},"size":1.961211919784546,"orthographic":false}